caispp/ImageClassifier.py
caispp/__init__.py
caispp-0.4.10.egg-info/PKG-INFO
caispp-0.4.10.egg-info/SOURCES.txt
caispp-0.4.10.egg-info/dependency_links.txt
caispp-0.4.10.egg-info/requires.txt
caispp-0.4.10.egg-info/top_level.txt
caispp-0.4.8-py3.7.egg-info/PKG-INFO
caispp-0.4.8-py3.7.egg-info/SOURCES.txt
caispp-0.4.8-py3.7.egg-info/dependency_links.txt
caispp-0.4.8-py3.7.egg-info/requires.txt
caispp-0.4.8-py3.7.egg-info/top_level.txt
caispp-0.4.8.egg-info/PKG-INFO
caispp-0.4.8.egg-info/SOURCES.txt
caispp-0.4.8.egg-info/dependency_links.txt
caispp-0.4.8.egg-info/requires.txt
caispp-0.4.8.egg-info/top_level.txt
caispp-0.4.10.dist-info/LICENSE
caispp-0.4.10.dist-info/METADATA
caispp-0.4.10.dist-info/WHEEL
caispp-0.4.10.dist-info/top_level.txt
caispp-0.4.8.dist-info/dependency_links.txt
caispp-0.4.8.dist-info/top_level.txt
caispp-0.4.10.dist-info/RECORD
