Metadata-Version: 2.1
Name: caispp
Version: 0.4.10
Summary: High level ML library used in CAIS++ Curriculum
Home-page: https://github.com/zanedurante/caispp
Author: Zane Durante
Author-email: zanedurante@gmail.com
License: UNKNOWN
Platform: UNKNOWN
Classifier: Programming Language :: Python :: 3
Classifier: License :: OSI Approved :: MIT License
Classifier: Operating System :: OS Independent
Requires-Dist: numpy (==1.16.4)
Requires-Dist: tensorflow (>=2.0)
Requires-Dist: Pillow
Requires-Dist: matplotlib
Requires-Dist: sklearn
Requires-Dist: pandas
Requires-Dist: gast (>=0.2.2)
